{"cameraMode":{"drawMode":0,"name":"Shaded","section":"Shading Mode"},"sceneLighting":false,"audioPlay":false,"sceneViewState":{"showFog":true,"showMaterialUpdate":false,"showSkybox":false,"showFlares":true,"showImageEffects":true,"showParticleSystems":true},"in2DMode":false,"pivot":{"x":2.815521240234375,"y":19.578693389892579,"z":-0.17971253395080567},"rotation":{"x":0.48479193449020388,"y":0.02754196710884571,"z":-0.015276752412319184,"w":0.8740672469139099},"size":1.4289418458938599,"orthographic":false}